tintx/__init__.py
tintx/cli.py
tintx/config.py
tintx/grid_utils.py
tintx/helpers.py
tintx/matching.py
tintx/objects.py
tintx/phase_correlation.py
tintx/reader.py
tintx/tracks.py
tintx/types.py
tintx/visualization.py
tintx/test/__init__.py
tintx/test/conftest.py
tintx/test/test_cli.py
tintx/test/test_config.py
tintx/test/test_tracking.py
tintx/test/test_utils.py
tintx/test/test_visualisation.py
tintx-2022.12.2.dist-info/LICENSE
tintx-2022.12.2.dist-info/METADATA
tintx-2022.12.2.dist-info/WHEEL
tintx-2022.12.2.dist-info/entry_points.txt
tintx-2022.12.2.dist-info/top_level.txt
tintx-2022.12.2.dist-info/RECORD
