Metadata-Version: 2.1
Name: tintx
Version: 2022.12.2
Summary: Tracking facility to track rainfall and other non-continous data.
Home-page: https://github.com/antarcticrainforest/tintX
Author: Martin Bergemann
Author-email: bergemann@dkrz.de
License: BSD-3-Clause
Project-URL: Documentation, https://tintx.readthedocs.io/en/latest/
Project-URL: Issues, https://github.com/antarcticrainforest/tintX/issues
Project-URL: Source, https://github.com/antarcticrainforest/tintX
Classifier: Development Status :: 4 - Beta
Classifier: Environment :: Console
Classifier: Intended Audience :: Developers
Classifier: Intended Audience :: Science/Research
Classifier: License :: OSI Approved :: BSD License
Classifier: Operating System :: POSIX :: Linux
Classifier: Programming Language :: Python :: 3
Classifier: Programming Language :: Python :: 3.7
Classifier: Programming Language :: Python :: 3.8
Classifier: Programming Language :: Python :: 3.9
Classifier: Programming Language :: Python :: 3.10
Classifier: Topic :: Scientific/Engineering :: Physics
Classifier: Topic :: Scientific/Engineering :: Atmospheric Science
Requires-Python: >=3.7
License-File: LICENSE
Requires-Dist: cartopy
Requires-Dist: click
Requires-Dist: cftime
Requires-Dist: dask
Requires-Dist: geopandas
Requires-Dist: matplotlib
Requires-Dist: netCDF4
Requires-Dist: numpy
Requires-Dist: pandas
Requires-Dist: rasterio
Requires-Dist: scipy
Requires-Dist: shapely
Requires-Dist: tables
Requires-Dist: tqdm
Requires-Dist: typing-extensions
Requires-Dist: xarray
Provides-Extra: docs
Requires-Dist: bash-kernel ; extra == 'docs'
Requires-Dist: black ; extra == 'docs'
Requires-Dist: ipython ; extra == 'docs'
Requires-Dist: ipywidgets ; extra == 'docs'
Requires-Dist: h5netcdf ; extra == 'docs'
Requires-Dist: mypy ; extra == 'docs'
Requires-Dist: nbsphinx ; extra == 'docs'
Requires-Dist: pytest ; extra == 'docs'
Requires-Dist: recommonmark ; extra == 'docs'
Requires-Dist: sphinx ; extra == 'docs'
Requires-Dist: sphinxcontrib-github-alt ; extra == 'docs'
Requires-Dist: sphinx-execute-code-python3 ; extra == 'docs'
Requires-Dist: sphinx-rtd-theme ; extra == 'docs'
Provides-Extra: tests
Requires-Dist: bash-kernel ; extra == 'tests'
Requires-Dist: black ; extra == 'tests'
Requires-Dist: flake8 ; extra == 'tests'
Requires-Dist: isort ; extra == 'tests'
Requires-Dist: mypy ; extra == 'tests'
Requires-Dist: nbval ; extra == 'tests'
Requires-Dist: pytest ; extra == 'tests'
Requires-Dist: pytest-env ; extra == 'tests'
Requires-Dist: pytest-cov ; extra == 'tests'
Requires-Dist: pytest-xdist ; extra == 'tests'
Requires-Dist: testpath ; extra == 'tests'
